lljz_tools/__init__.py
lljz_tools/__main__.py
lljz_tools/color.py
lljz_tools/compare.py
lljz_tools/console_table.py
lljz_tools/decorators.py
lljz_tools/log_manager.py
lljz_tools/pkg.py
lljz_tools/string_utils.py
lljz_tools/track_print.py
lljz_tools/client/__init__.py
lljz_tools/client/es_client.py
lljz_tools/client/http_client.py
lljz_tools/client/mongo_client.py
lljz_tools/client/mysql_client.py
lljz_tools/client/redis_client.py
lljz_tools/client/utils.py
lljz_tools/excel/__init__.py
lljz_tools/excel/reader.py
lljz_tools/excel/writer.py
lljz_tools/excel_template/__init__.py
lljz_tools/excel_template/columns.py
lljz_tools/excel_template/template.py
lljz_tools/models/__init__.py
lljz_tools/models/base_model.py
lljz_tools/random_tools/__init__.py
lljz_tools/simple_pref_test/__init__.py
lljz_tools/simple_pref_test/_task.py
lljz_tools/simple_pref_test/core.py
lljz_tools/simple_pref_test/runner.py
lljz_tools/simple_pref_test/task_config.py
lljz_tools/simple_pref_test/utils.py
lljz_tools/source/echart.js
lljz_tools/source/result.html
lljz_tools-0.3.13.dist-info/METADATA
lljz_tools-0.3.13.dist-info/WHEEL
lljz_tools-0.3.13.dist-info/licenses/LICENSE
lljz_tools-0.3.13.dist-info/RECORD
