Metadata-Version: 2.4
Name: lljz_tools
Version: 0.3.13
Summary: 常用工具方法的封装
Author-email: liulangjuanzhou <liulangjuanzhou@gmail.com>
License-File: LICENSE
Requires-Python: >=3.10
Requires-Dist: better-exceptions>=0.3.3
Requires-Dist: colorlog>=6.9.0
Requires-Dist: concurrent-log-handler>=0.9.23
Requires-Dist: jinja2>=3.1.5
Requires-Dist: openpyxl>=3.1.5
Requires-Dist: python-dateutil>=2.9.0.post0
Requires-Dist: requests>=2.32.3
